{
	"A": [
		"really",
		"happily",
		"unwillingly",
		"excitedly",
		"deeply",
		"badly",
		"earnestly",
		"greatly",
		"nervously",
		"entirely",
		"fearlessly",
		"wholly",
		"delightfully",
		"dearly",
		"desperately ",
		"wearily",
		"worriedly ",
		"furiously",
		"frenetically",
		"grumpily",
		"oddly",
		"frankly",
		"openly",
		"daintily",
		"guiltily",
		"harshly",
		"enviously ",
		"dreamily",
		"fervently",
		"fully",
		"foolishly",
		"generally",
		"intensely",
		"darkly",
		"continually",
		"powerfully",
		"ferociously",
		"proudly",
		"longingly",
		"determinedly",
		"doggedly",
		"gleefully",
		"gently",
		"heartily",
		"bravely",
		"anxiously",
		"calmly",
		"clumsily",
		"boldly"
	],
	"B": [
		"wish",
		"dread",
		"hope",
		"suspect",
		"suppose",
		"trust",
		"desire",
		"expect",
		"assume",
		"believe",
		"fear",
		"foresee",
		"anticipate",
		"prophesy",
		"forecast",
		"conjecture",
		"know",
		"fancy",
		"think",
		"fantasize",
		"surmise",
		"guess",
		"postulate",
		"admit",
		"accept",
		"affirm",
		"declare",
		"guarantee",
		"maintain",
		"profess",
		"insist",
		"imagine"
	],
	"C": [
		"unfathomably",
		"incredibly",
		"unforgettably",
		"strangely",
		"uncommonly",
		"astonishingly",
		"fabulously",
		"especially",
		"remarkably",
		"extremely",
		"exceptionally",
		"unusually",
		"exceedingly",
		"extraordinarily",
		"hugely",
		"highly",
		"terribly",
		"terrifically",
		"utterly",
		"overly",
		"intensely",
		"awfully",
		"strikingly",
		"totally",
		"perfectly",
		"amazingly",
		"completely",
		"thoroughly",
		"profoundly",
		"pleasantly",
		"ridiculously"
	],
	"D": [
		"spicy",
		"sus",
		"salty",
		"extra",
		"lit",
		"classy",
		"clever",
		"deadly",
		"hip",
		"bland",
		"adventurous",
		"brave",
		"courageous",
		"exuberant",
		"gaudy",
		"gritty",
		"mysterious",
		"impressive",
		"terrible",
		"outrageous",
		"tricky",
		"wicked",
		"zippy",
		"fresh",
		"crazy",
		"amazing",
		"incredible",
		"profound",
		"expansive",
		"real",
		"strange",
		"foolish",
		"robust",
		"timely",
		"genuine",
		"noob",
		"dope",
		"kickass",
		"rad",
		"spiffy",
		"stellar",
		"slick",
		"wild",
		"uber"
	],
	"E": [
		"amazing",
		"awesome",
		"extreme",
		"excellent",
		"well-deserved",
		"incredible",
		"happy",
		"charming",
		"ideal",
		"agreeable",
		"colourful",
		"interesting",
		"awkward",
		"astonishing",
		"astounding",
		"elegant",
		"fancy",
		"fantastic",
		"captivating",
		"blissful",
		"breath-taking",
		"spectacular",
		"stunning",
		"miraculous",
		"majestic",
		"magnificent",
		"stupefying",
		"wondrous",
		"sublime",
		"inspiring",
		"splendid",
		"dramatic",
		"remarkable",
		"grand",
		"stupendous",
		"prodigious",
		"sensational",
		"staggering",
		"exciting",
		"good",
		"juicy"
	],
	"F": [
		"own",
		"ace",
		"achieve",
		"reach",
		"manage",
		"succeed at",
		"master",
		"excel in",
		"nail",
		"execute",
		"pull off",
		"accomplish",
		"attain",
		"fulfil",
		"satisfy",
		"perform at",
		"carry out",
		"work at",
		"engage in",
		"follow through with"
	],
	"G": [
		"unsure",
		"uncertain",
		"confuzzled",
		"confused",
		"confounded",
		"stunned",
		"bewildered",
		"dazed",
		"fogged",
		"muddleheaded",
		"stupefied",
		"mixed-up",
		"pixilated",
		"raddled",
		"bemused",
		"zonked",
		"perplexed",
		"muddled",
		"baffled",
		"flummoxed",
		"bamboozled",
		"puzzled",
		"amazed",
		"surprised",
		"astonished",
		"flabbergasted",
		"sceptical",
		"doubting",
		"suspicious",
		"overwhelmed",
		"awed",
		"unconvinced"
	],
	"H": [
		"upsetting",
		"annoying",
		"frustrating",
		"irritating",
		"disturbing",
		"provoking",
		"troublesome",
		"exasperating",
		"maddening",
		"irksome",
		"bothersome",
		"vexatious",
		"aggravating",
		"displeasing",
		"bedevilling",
		"peeving",
		"nagging",
		"worrisome",
		"burdensome",
		"disquieting",
		"galling",
		"infuriating",
		"trying",
		"teasing",
		"unwelcome",
		"disagreeable"
	],
	"I": [
		"quickly",
		"swiftly",
		"speedily",
		"rapidly",
		"hastily",
		"promptly",
		"briskly",
		"expeditiously",
		"immediately",
		"instantly",
		"energetically",
		"vigorously",
		"efficiently",
		"nimbly",
		"smartly",
		"actively",
		"readily",
		"willingly",
		"freely",
		"voluntarily",
		"eagerly",
		"cheerfully",
		"happily",
		"earnestly",
		"nervously",
		"fearlessly",
		"delightfully",
		"daintily",
		"fully",
		"ferociously",
		"proudly",
		"determinedly",
		"doggedly",
		"gleefully",
		"heartily",
		"calmly",
		"boldly"
	],
	"J": [
		"act",
		"take steps",
		"respond",
		"address this",
		"do something",
		"get my butt in motion",
		"get cracking",
		"get the ball rolling",
		"take the plunge",
		"take the bull by the horns",
		"take the initiative",
		"take action",
		"make a move",
		"get stuck in",
		"dive in",
		"be decisive",
		"do my thing",
		"go for it",
		"get going"
	],
	"K": [
		"ASAP",
		"soon",
		"post-haste",
		"at once",
		"directly ",
		"promptly",
		"straightaway",
		"pronto",
		"rapidly",
		"quickly",
		"full tilt",
		"hastily",
		"double-quick",
		"as in yesterday",
		"chop-chop",
		"right quick",
		"interfrastically",
		"quickfast",
		"like wildfire",
		"lickety-split",
		"in short order",
		"off the bat",
		"forthwith",
		"right now",
		"now now",
		"just now",
		"in nothing flat",
		"in a jiffy",
		"like nobody's business",
		"on the double"
	],
	"L": [
		"What the heck is",
		"What even is",
		"What on earth is",
		"What in tarnation is",
		"What the dickens is",
		"What the fluff is",
		"Confusion reigns about",
		"Questions about concerning",
		"My brain is broken about",
		"Who knew",
		"Not sure if",
		"Huh, I never knew"
	],
	"M": [
		"helpful",
		"unhelpful",
		"confusing",
		"incredible",
		"excellent",
		"awesome",
		"amazing",
		"ideal",
		"fantastic",
		"spectacular",
		"stunning",
		"terrible",
		"the worst",
		"wondrous",
		"sublime",
		"magnificent",
		"stupefying",
		"inspiring",
		"splendid",
		"dramatic",
		"remarkable",
		"grand",
		"stupendous",
		"prodigious",
		"sensational",
		"staggering",
		"exciting",
		"good",
		"juicy",
		"dreadful ",
		"horrible",
		"awful",
		"horrifying",
		"horrendous",
		"shocking",
		"ghastly",
		"appalling",
		"gruesome",
		"rotten",
		"nightmarish",
		"unwelcome",
		"vile",
		"fair",
		"ok",
		"average",
		"pleasing",
		"passable",
		"all right",
		"satisfactory",
		"unexceptional",
		"up to scratch",
		"insane",
		"crazy",
		"cool",
		"bad",
		"frightful",
		"scary",
		"sad",
		"unnerving",
		"difficult",
		"slick",
		"wizard",
		"primo",
		"corking",
		"marvellous",
		"decent",
		"fine"
	],
	"N": [
		"incredible",
		"excellent",
		"awesome",
		"amazing",
		"fantastic",
		"spectacular",
		"terrible",
		"wondrous",
		"sublime",
		"magnificent",
		"stupefying",
		"inspiring",
		"splendid",
		"remarkable",
		"grand",
		"stupendous",
		"prodigious",
		"sensational",
		"staggering",
		"good",
		"confused",
		"excited",
		"dreadful ",
		"horrible",
		"awful",
		"horrendous",
		"shocking",
		"ghastly",
		"appalling",
		"gruesome",
		"rotten",
		"nightmarish",
		"unwelcome",
		"vile",
		"fair",
		"ok",
		"average",
		"all right",
		"satisfactory",
		"unexceptional",
		"up to scratch",
		"insane",
		"crazy",
		"cool",
		"bad",
		"sad",
		"slick",
		"marvellous",
		"decent",
		"fine"
	],
	"O": [
		"spicy",
		"sus",
		"salty",
		"extra",
		"lit",
		"weird",
		"wack",
		"deadly",
		"hip",
		"bland",
		"adventurous",
		"brave",
		"courageous",
		"exuberant",
		"gaudy",
		"gritty",
		"impressive",
		"terrible",
		"outrageous",
		"tricky",
		"wicked",
		"zippy",
		"fresh",
		"crazy",
		"amazing",
		"incredible",
		"profound",
		"real",
		"strange",
		"dope",
		"kickass",
		"rad",
		"spiffy",
		"stellar",
		"slick",
		"wild",
		"uber",
		"bad",
		"sad",
		"lousy",
		"poor",
		"crummy",
		"below par",
		"second-rate",
		"meh",
		"lame"
	],
	"P": [
		"owned",
		"aced",
		"excelled at",
		"struggled with",
		"hated",
		"nailed",
		"loved",
		"succeeded at",
		"enjoyed",
		"despised",
		"did well at",
		"did badly at",
		"failed at",
		"managed ",
		"mastered",
		"achieved",
		"wrestled with",
		"monitored"
	]
}